cell_imaging_utils/__init__.py
cell_imaging_utils/data_structures/__init__.py
cell_imaging_utils/data_structures/singleton.py
cell_imaging_utils/datasets_metadata/__init__.py
cell_imaging_utils/datasets_metadata/datasetes_metadata_abstract.py
cell_imaging_utils/datasets_metadata/dict/__init__.py
cell_imaging_utils/datasets_metadata/dict/datasetes_metadata_abstract_dict.py
cell_imaging_utils/datasets_metadata/dict/datasetes_metadata_pickle.py
cell_imaging_utils/datasets_metadata/table/__init__.py
cell_imaging_utils/datasets_metadata/table/datasetes_metadata_abstract_table.py
cell_imaging_utils/datasets_metadata/table/datasetes_metadata_csv.py
cell_imaging_utils/image/__init__.py
cell_imaging_utils/image/image_utils.py
cell_imaging_utils/plots/__init__.py
cell_imaging_utils/plots/plot_utils.py
cell_imaging_utils-1.16.8.dist-info/licenses/LICENSE
tests/__init__.py
tests/test_datasets_metadata.py
tests/test_image_utils.py
tests/test_plot_utils.py
cell_imaging_utils-1.16.8.dist-info/METADATA
cell_imaging_utils-1.16.8.dist-info/WHEEL
cell_imaging_utils-1.16.8.dist-info/top_level.txt
cell_imaging_utils-1.16.8.dist-info/RECORD
