Metadata-Version: 2.4
Name: cell_imaging_utils
Version: 1.16.8
Home-page: https://github.com/lionben89/BGU_cell_imaging_utils
Author: Lion Ben Nedava
Author-email: lionben89@gmail.com
License: MIT
Keywords: cell_imaging_utils
Requires-Python: >=3.6
License-File: LICENSE
Requires-Dist: matplotlib
Requires-Dist: numpy
Requires-Dist: imageio
Requires-Dist: scikit-image>=0.16.2
Requires-Dist: quilt3
Requires-Dist: bumpversion
Requires-Dist: twine
Requires-Dist: setuptools>=42
Requires-Dist: wheel
Requires-Dist: pandas
Requires-Dist: multipledispatch
Dynamic: author
Dynamic: author-email
Dynamic: description
Dynamic: description-content-type
Dynamic: home-page
Dynamic: keywords
Dynamic: license
Dynamic: license-file
Dynamic: requires-dist
Dynamic: requires-python
